endomill/_EndomillHaltException.py
endomill/_SigHandlerContextManager.py
endomill/__init__.py
endomill/_halt.py
endomill/_try_instantiate_one.py
endomill/_unlink_missing_ok.py
endomill/add_instance_outpath.py
endomill/in_interactive_notebook.py
endomill/instantiate_one.py
endomill/instantiate_over.py
endomill-0.1.3.dist-info/AUTHORS.rst
endomill-0.1.3.dist-info/LICENSE
endomill-0.1.3.dist-info/METADATA
endomill-0.1.3.dist-info/WHEEL
endomill-0.1.3.dist-info/top_level.txt
endomill-0.1.3.dist-info/RECORD
