Metadata-Version: 2.1
Name: endomill
Version: 0.1.3
Summary: endomill lets a Jupyter notebook instantiate itself as a papermill template
Home-page: https://github.com/mmore500/endomill
Author: Matthew Andres Moreno
Author-email: m.more500@gmail.com
License: MIT license
Keywords: endomill
Platform: UNKNOWN
Classifier: Development Status :: 2 - Pre-Alpha
Classifier: Intended Audience :: Developers
Classifier: License :: OSI Approved :: MIT License
Classifier: Natural Language :: English
Classifier: Programming Language :: Python :: 3
Classifier: Programming Language :: Python :: 3.7
Classifier: Programming Language :: Python :: 3.8
Classifier: Programming Language :: Python :: 3.9
Requires-Python: >=3.6
Requires-Dist: IPython (>=7.3.8)
Requires-Dist: keyname (>=0.4.1)
Requires-Dist: nbmetalog (>=0.2.5)
Requires-Dist: papermill[all] (>=2.3.4)
Requires-Dist: python-slugify (>=6.1.1)
